sec_parser/__init__.py
sec_parser/exceptions.py
sec_parser/processing_engine/__init__.py
sec_parser/processing_engine/core.py
sec_parser/processing_engine/html_tag.py
sec_parser/processing_engine/html_tag_parser.py
sec_parser/processing_engine/processing_log.py
sec_parser/processing_engine/types.py
sec_parser/processing_steps/__init__.py
sec_parser/processing_steps/abstract_classes/__init__.py
sec_parser/processing_steps/abstract_classes/abstract_element_batch_processing_step.py
sec_parser/processing_steps/abstract_classes/abstract_elementwise_processing_step.py
sec_parser/processing_steps/abstract_classes/abstract_processing_step.py
sec_parser/processing_steps/abstract_classes/processing_context.py
sec_parser/processing_steps/empty_element_classifier.py
sec_parser/processing_steps/highlighted_text_classifier.py
sec_parser/processing_steps/image_classifier.py
sec_parser/processing_steps/individual_semantic_element_extractor/__init__.py
sec_parser/processing_steps/individual_semantic_element_extractor/individual_semantic_element_extractor.py
sec_parser/processing_steps/individual_semantic_element_extractor/single_element_checks/__init__.py
sec_parser/processing_steps/individual_semantic_element_extractor/single_element_checks/abstract_single_element_check.py
sec_parser/processing_steps/individual_semantic_element_extractor/single_element_checks/image_check.py
sec_parser/processing_steps/individual_semantic_element_extractor/single_element_checks/table_check.py
sec_parser/processing_steps/individual_semantic_element_extractor/single_element_checks/top_section_title_check.py
sec_parser/processing_steps/individual_semantic_element_extractor/single_element_checks/xbrl_tag_check.py
sec_parser/processing_steps/introductory_section_classifier.py
sec_parser/processing_steps/page_header_classifier.py
sec_parser/processing_steps/page_number_classifier.py
sec_parser/processing_steps/supplementary_text_classifier.py
sec_parser/processing_steps/table_classifier.py
sec_parser-0.58.1.dist-info/LICENSE
sec_parser-0.58.1.dist-info/METADATA
sec_parser-0.58.1.dist-info/WHEEL
sec_parser-0.58.1.dist-info/RECORD
