Metadata-Version: 2.1
Name: sec-parser
Version: 0.58.1
Summary: Parse SEC EDGAR HTML documents into a tree of elements that correspond to the visual structure of the document.
Home-page: https://github.com/alphanome-ai/sec-parser
License: MIT
Author: Alphanome.AI
Author-email: info@alphanome.ai
Requires-Python: >=3.9, !=2.7.*, !=3.0.*, !=3.1.*, !=3.2.*, !=3.3.*, !=3.4.*, !=3.5.*, !=3.6.*, !=3.7.*, !=3.8.*
Classifier: Development Status :: 4 - Beta
Classifier: Intended Audience :: Developers
Classifier: Intended Audience :: Financial and Insurance Industry
Classifier: Intended Audience :: Science/Research
Classifier: License :: OSI Approved :: MIT License
Classifier: Natural Language :: English
Classifier: Operating System :: OS Independent
Classifier: Programming Language :: Python :: 3
Classifier: Programming Language :: Python :: 3.9
Classifier: Programming Language :: Python :: 3.10
Classifier: Programming Language :: Python :: 3.11
Classifier: Topic :: Office/Business :: Financial
Classifier: Topic :: Scientific/Engineering :: Artificial Intelligence
Classifier: Topic :: Scientific/Engineering :: Information Analysis
Classifier: Topic :: Software Development :: Libraries :: Python Modules
Classifier: Topic :: Text Processing :: Markup :: HTML
Requires-Dist: beautifulsoup4 (>=4.12.3,<5.0.0)
Requires-Dist: cssutils (>=2.11.1,<3.0.0)
Requires-Dist: frozendict (>=2.4.4,<3.0.0)
Requires-Dist: loguru (>=0.7.2,<0.8.0)
Requires-Dist: lxml (>=5.2.2,<6.0.0)
Requires-Dist: pandas (>=2.2.2,<3.0.0)
Requires-Dist: sec-downloader (>=0.11.1,<0.12.0)
Requires-Dist: tabulate (>=0.9.0,<0.10.0)
Requires-Dist: xxhash (>=3.4.1,<4.0.0)
Project-URL: Repository, https://github.com/alphanome-ai/sec-parser
